pyarrow/__init__.pxd
pyarrow/__init__.py
pyarrow/_acero.cpython-39-x86_64-linux-gnu.so
pyarrow/_acero.pxd
pyarrow/_acero.pyx
pyarrow/_compute.cpython-39-x86_64-linux-gnu.so
pyarrow/_compute.pxd
pyarrow/_compute.pyx
pyarrow/_compute_docstrings.py
pyarrow/_csv.cpython-39-x86_64-linux-gnu.so
pyarrow/_csv.pxd
pyarrow/_csv.pyx
pyarrow/_cuda.pxd
pyarrow/_cuda.pyx
pyarrow/_dataset.cpython-39-x86_64-linux-gnu.so
pyarrow/_dataset.pxd
pyarrow/_dataset.pyx
pyarrow/_dataset_orc.cpython-39-x86_64-linux-gnu.so
pyarrow/_dataset_orc.pyx
pyarrow/_dataset_parquet.cpython-39-x86_64-linux-gnu.so
pyarrow/_dataset_parquet.pxd
pyarrow/_dataset_parquet.pyx
pyarrow/_dataset_parquet_encryption.cpython-39-x86_64-linux-gnu.so
pyarrow/_dataset_parquet_encryption.pyx
pyarrow/_feather.cpython-39-x86_64-linux-gnu.so
pyarrow/_feather.pyx
pyarrow/_flight.cpython-39-x86_64-linux-gnu.so
pyarrow/_flight.pyx
pyarrow/_fs.cpython-39-x86_64-linux-gnu.so
pyarrow/_fs.pxd
pyarrow/_fs.pyx
pyarrow/_gcsfs.cpython-39-x86_64-linux-gnu.so
pyarrow/_gcsfs.pyx
pyarrow/_hdfs.cpython-39-x86_64-linux-gnu.so
pyarrow/_hdfs.pyx
pyarrow/_hdfsio.cpython-39-x86_64-linux-gnu.so
pyarrow/_hdfsio.pyx
pyarrow/_json.cpython-39-x86_64-linux-gnu.so
pyarrow/_json.pxd
pyarrow/_json.pyx
pyarrow/_orc.cpython-39-x86_64-linux-gnu.so
pyarrow/_orc.pxd
pyarrow/_orc.pyx
pyarrow/_parquet.cpython-39-x86_64-linux-gnu.so
pyarrow/_parquet.pxd
pyarrow/_parquet.pyx
pyarrow/_parquet_encryption.cpython-39-x86_64-linux-gnu.so
pyarrow/_parquet_encryption.pxd
pyarrow/_parquet_encryption.pyx
pyarrow/_pyarrow_cpp_tests.cpython-39-x86_64-linux-gnu.so
pyarrow/_pyarrow_cpp_tests.pxd
pyarrow/_pyarrow_cpp_tests.pyx
pyarrow/_s3fs.cpython-39-x86_64-linux-gnu.so
pyarrow/_s3fs.pyx
pyarrow/_substrait.cpython-39-x86_64-linux-gnu.so
pyarrow/_substrait.pyx
pyarrow/acero.py
pyarrow/array.pxi
pyarrow/benchmark.pxi
pyarrow/benchmark.py
pyarrow/builder.pxi
pyarrow/cffi.py
pyarrow/compat.pxi
pyarrow/compute.py
pyarrow_cramjam-14.1.5.dist-info/LICENSE.txt
pyarrow_cramjam-14.1.5.dist-info/METADATA
pyarrow_cramjam-14.1.5.dist-info/NOTICE.txt
pyarrow_cramjam-14.1.5.dist-info/WHEEL
pyarrow_cramjam-14.1.5.dist-info/top_level.txt
pyarrow_cramjam-14.1.5.dist-info/RECORD
